odoo10_addon_product_supplierinfo_for_customer-10.0.3.0.1.99.dev4-py2.7-nspkg.pth
odoo/addons/product_supplierinfo_for_customer/README.rst
odoo/addons/product_supplierinfo_for_customer/__init__.py
odoo/addons/product_supplierinfo_for_customer/__manifest__.py
odoo/addons/product_supplierinfo_for_customer/demo/product_demo.xml
odoo/addons/product_supplierinfo_for_customer/i18n/de.po
odoo/addons/product_supplierinfo_for_customer/i18n/es.po
odoo/addons/product_supplierinfo_for_customer/i18n/fr.po
odoo/addons/product_supplierinfo_for_customer/i18n/product_supplierinfo_for_customer.pot
odoo/addons/product_supplierinfo_for_customer/i18n/sl.po
odoo/addons/product_supplierinfo_for_customer/models/__init__.py
odoo/addons/product_supplierinfo_for_customer/models/pricelist.py
odoo/addons/product_supplierinfo_for_customer/models/product_product.py
odoo/addons/product_supplierinfo_for_customer/models/product_supplierinfo.py
odoo/addons/product_supplierinfo_for_customer/models/product_template.py
odoo/addons/product_supplierinfo_for_customer/models/res_partner.py
odoo/addons/product_supplierinfo_for_customer/static/description/icon.png
odoo/addons/product_supplierinfo_for_customer/tests/__init__.py
odoo/addons/product_supplierinfo_for_customer/tests/test_product_supplierinfo_for_customer.py
odoo/addons/product_supplierinfo_for_customer/views/product_view.xml
odoo10_addon_product_supplierinfo_for_customer-10.0.3.0.1.99.dev4.dist-info/METADATA
odoo10_addon_product_supplierinfo_for_customer-10.0.3.0.1.99.dev4.dist-info/RECORD
odoo10_addon_product_supplierinfo_for_customer-10.0.3.0.1.99.dev4.dist-info/WHEEL
odoo10_addon_product_supplierinfo_for_customer-10.0.3.0.1.99.dev4.dist-info/namespace_packages.txt
odoo10_addon_product_supplierinfo_for_customer-10.0.3.0.1.99.dev4.dist-info/top_level.txt
