Metadata-Version: 2.1
Name: odoo10-addon-product-supplierinfo-for-customer
Version: 10.0.3.0.1.99.dev4
Summary: Allows to define prices for customers in the products
Home-page: https://github.com/OCA/product-attribute
Author: AvanzOSC, Tecnativa, Odoo Community Association (OCA)
Author-email: support@odoo-community.org
License: AGPL-3
Platform: UNKNOWN
Classifier: Programming Language :: Python
Classifier: Framework :: Odoo
Classifier: License :: OSI Approved :: GNU Affero General Public License v3
Requires-Python: ~=2.7
Requires-Dist: odoo (<10.1dev,>=10.0)
